odoo/addons/stock_picking_invoicing/README.rst
odoo/addons/stock_picking_invoicing/__init__.py
odoo/addons/stock_picking_invoicing/__manifest__.py
odoo/addons/stock_picking_invoicing/demo/stock_picking_demo.xml
odoo/addons/stock_picking_invoicing/i18n/de.po
odoo/addons/stock_picking_invoicing/i18n/es.po
odoo/addons/stock_picking_invoicing/i18n/fr.po
odoo/addons/stock_picking_invoicing/i18n/pt_BR.po
odoo/addons/stock_picking_invoicing/i18n/sl.po
odoo/addons/stock_picking_invoicing/i18n/stock_picking_invoicing.pot
odoo/addons/stock_picking_invoicing/models/__init__.py
odoo/addons/stock_picking_invoicing/models/account_move.py
odoo/addons/stock_picking_invoicing/models/stock_invoice_state_mixin.py
odoo/addons/stock_picking_invoicing/models/stock_move.py
odoo/addons/stock_picking_invoicing/models/stock_picking.py
odoo/addons/stock_picking_invoicing/models/stock_picking_type.py
odoo/addons/stock_picking_invoicing/readme/CONTRIBUTORS.rst
odoo/addons/stock_picking_invoicing/readme/DESCRIPTION.rst
odoo/addons/stock_picking_invoicing/readme/HISTORY.rst
odoo/addons/stock_picking_invoicing/readme/INSTALL.rst
odoo/addons/stock_picking_invoicing/readme/USAGE.rst
odoo/addons/stock_picking_invoicing/static/description/icon.png
odoo/addons/stock_picking_invoicing/static/description/index.html
odoo/addons/stock_picking_invoicing/tests/__init__.py
odoo/addons/stock_picking_invoicing/tests/test_picking_invoicing.py
odoo/addons/stock_picking_invoicing/views/stock_move.xml
odoo/addons/stock_picking_invoicing/views/stock_picking.xml
odoo/addons/stock_picking_invoicing/views/stock_picking_type.xml
odoo/addons/stock_picking_invoicing/wizards/__init__.py
odoo/addons/stock_picking_invoicing/wizards/stock_invoice_onshipping.py
odoo/addons/stock_picking_invoicing/wizards/stock_invoice_onshipping_view.xml
odoo/addons/stock_picking_invoicing/wizards/stock_return_picking.py
odoo/addons/stock_picking_invoicing/wizards/stock_return_picking_view.xml
odoo13_addon_stock_picking_invoicing-13.0.3.1.1.dist-info/METADATA
odoo13_addon_stock_picking_invoicing-13.0.3.1.1.dist-info/WHEEL
odoo13_addon_stock_picking_invoicing-13.0.3.1.1.dist-info/top_level.txt
odoo13_addon_stock_picking_invoicing-13.0.3.1.1.dist-info/RECORD
